{
    "features": [
        {
            "geometry": {
                "coordinates": [
                    -2.579302,
                    51.157675
                ],
                "type": "Point"
            },
            "properties": {
                "busy_description": null,
                "busy_title": null,
                "description": null,
                "display_on_map": true,
                "is_busy": false,
                "is_in_market": false,
                "name": "Lost Property",
                "tags": []
            },
            "type": "Feature"
        }
    ],
    "type": "FeatureCollection"
}