{
    "type": "FeatureCollection",
    "features": [
        {
            "type": "Feature",
            "properties": {
                "name": "Festival T-shirts",
                "description": "Official T-shirts & Hoodies made with Fairtrade & Organic Cotton",
                "tags": [
                    "Official Merchandise"
                ],
                "is_in_market": true,
                "is_busy": false,
                "busy_title": null,
                "busy_description": null,
                "display_on_map": true
            },
            "geometry": {
                "type": "Point",
                "coordinates": [
                    -2.585354,
                    51.152962
                ]
            }
        },
        {
            "type": "Feature",
            "properties": {
                "name": "Festival T-shirts",
                "description": "Official T-shirts & Hoodies made with Fairtrade & Organic Cotton",
                "tags": [
                    "Official Merchandise"
                ],
                "is_in_market": true,
                "is_busy": false,
                "busy_title": null,
                "busy_description": null,
                "display_on_map": true
            },
            "geometry": {
                "type": "Point",
                "coordinates": [
                    -2.583126,
                    51.151478
                ]
            }
        },
        {
            "type": "Feature",
            "properties": {
                "name": "Festival T-shirts",
                "description": "Official T-shirts & Hoodies made with Fairtrade & Organic Cotton",
                "tags": [
                    "Official Merchandise"
                ],
                "is_in_market": true,
                "is_busy": false,
                "busy_title": null,
                "busy_description": null,
                "display_on_map": true
            },
            "geometry": {
                "type": "Point",
                "coordinates": [
                    -2.581481,
                    51.153347
                ]
            }
        },
        {
            "type": "Feature",
            "properties": {
                "name": "Festival T-shirts",
                "description": "Official T-shirts & Hoodies made with Fairtrade & Organic Cotton",
                "tags": [
                    "Official Merchandise"
                ],
                "is_in_market": true,
                "is_busy": false,
                "busy_title": null,
                "busy_description": null,
                "display_on_map": true
            },
            "geometry": {
                "type": "Point",
                "coordinates": [
                    -2.589697,
                    51.155609
                ]
            }
        },
        {
            "type": "Feature",
            "properties": {
                "name": "Festival T-shirts",
                "description": "Official T-shirts & Hoodies made with Fairtrade & Organic Cotton",
                "tags": [
                    "Official Merchandise"
                ],
                "is_in_market": true,
                "is_busy": false,
                "busy_title": null,
                "busy_description": null,
                "display_on_map": true
            },
            "geometry": {
                "type": "Point",
                "coordinates": [
                    -2.585475,
                    51.154853
                ]
            }
        },
        {
            "type": "Feature",
            "properties": {
                "name": "Festival T-shirts",
                "description": "Official T-shirts & Hoodies made with Fairtrade & Organic Cotton",
                "tags": [
                    "Official Merchandise"
                ],
                "is_in_market": true,
                "is_busy": false,
                "busy_title": null,
                "busy_description": null,
                "display_on_map": true
            },
            "geometry": {
                "type": "Point",
                "coordinates": [
                    -2.589091,
                    51.152465
                ]
            }
        }
    ]
}