{
    "features": [
        {
            "geometry": {
                "coordinates": [
                    -2.59095,
                    51.145766
                ],
                "type": "Point"
            },
            "properties": {
                "busy_description": null,
                "busy_title": null,
                "description": "Places where anyone can go if they need some time away from it all",
                "display_on_map": true,
                "is_busy": false,
                "is_in_market": false,
                "name": "Worthy Rest",
                "tags": []
            },
            "type": "Feature"
        },
        {
            "geometry": {
                "coordinates": [
                    -2.593502,
                    51.155607
                ],
                "type": "Point"
            },
            "properties": {
                "busy_description": null,
                "busy_title": null,
                "description": "Places where anyone can go if they need some time away from it all",
                "display_on_map": true,
                "is_busy": false,
                "is_in_market": false,
                "name": "Worthy Rest",
                "tags": []
            },
            "type": "Feature"
        },
        {
            "geometry": {
                "coordinates": [
                    -2.578439,
                    51.157673
                ],
                "type": "Point"
            },
            "properties": {
                "busy_description": null,
                "busy_title": null,
                "description": "Places where anyone can go if they need some time away from it all",
                "display_on_map": true,
                "is_busy": false,
                "is_in_market": false,
                "name": "Worthy Rest",
                "tags": []
            },
            "type": "Feature"
        }
    ],
    "type": "FeatureCollection"
}